colorer/__init__.py
colorer/colors.py
colorer/main.py
colorer-1.0.2.dist-info/LICENSE
colorer-1.0.2.dist-info/METADATA
colorer-1.0.2.dist-info/WHEEL
colorer-1.0.2.dist-info/top_level.txt
colorer-1.0.2.dist-info/RECORD
