Metadata-Version: 2.1
Name: colorer
Version: 1.0.2
Summary: A simple and handy library for coloring strings.
Home-page: https://github.com/ALhorm/colorer
Author: ALhorm
Author-email: gladkoam@gmail.com
Classifier: Programming Language :: Python :: 3.11
Classifier: License :: OSI Approved :: MIT License
Classifier: Operating System :: OS Independent
Requires-Python: >=3.0
License-File: LICENSE
